{"filename": "getting_started/index.md", "lineno": 3, "status": "unchecked", "code": 0, "uri": "", "info": ""}
{"filename": "api_index.rst", "lineno": 1, "status": "unchecked", "code": 0, "uri": "#movement.analysis.kinematics.compute_acceleration", "info": ""}
{"filename": "api_index.rst", "lineno": 1, "status": "unchecked", "code": 0, "uri": "#movement.analysis.kinematics.compute_displacement", "info": ""}
{"filename": "api_index.rst", "lineno": 1, "status": "unchecked", "code": 0, "uri": "#movement.analysis.kinematics.compute_velocity", "info": ""}
{"filename": "api_index.rst", "lineno": 1, "status": "unchecked", "code": 0, "uri": "#movement.filtering.filter_by_confidence", "info": ""}
{"filename": "api_index.rst", "lineno": 1, "status": "unchecked", "code": 0, "uri": "#movement.filtering.interpolate_over_time", "info": ""}
{"filename": "api_index.rst", "lineno": 1, "status": "unchecked", "code": 0, "uri": "#movement.filtering.median_filter", "info": ""}
{"filename": "api_index.rst", "lineno": 1, "status": "unchecked", "code": 0, "uri": "#movement.filtering.report_nan_values", "info": ""}
{"filename": "api_index.rst", "lineno": 1, "status": "unchecked", "code": 0, "uri": "#movement.filtering.savgol_filter", "info": ""}
{"filename": "api/movement.io.load_poses.from_dlc_file.rst", "lineno": 17, "status": "unchecked", "code": 0, "uri": "#movement.io.load_poses.from_dlc_df", "info": ""}
{"filename": "api/movement.io.load_poses.from_dlc_df.rst", "lineno": 26, "status": "unchecked", "code": 0, "uri": "#movement.io.load_poses.from_dlc_file", "info": ""}
{"filename": "api_index.rst", "lineno": 1, "status": "unchecked", "code": 0, "uri": "#movement.io.load_poses.from_file", "info": ""}
{"filename": "api/movement.io.load_poses.from_file.rst", "lineno": 24, "status": "unchecked", "code": 0, "uri": "#movement.io.load_poses.from_lp_file", "info": ""}
{"filename": "api/movement.io.load_poses.from_file.rst", "lineno": 24, "status": "unchecked", "code": 0, "uri": "#movement.io.load_poses.from_sleap_file", "info": ""}
{"filename": "api/movement.io.save_poses.to_dlc_file.rst", "lineno": 32, "status": "unchecked", "code": 0, "uri": "#movement.io.save_poses.to_dlc_df", "info": ""}
{"filename": "api/movement.io.save_poses.to_dlc_df.rst", "lineno": 29, "status": "unchecked", "code": 0, "uri": "#movement.io.save_poses.to_dlc_file", "info": ""}
{"filename": "api_index.rst", "lineno": 1, "status": "unchecked", "code": 0, "uri": "#movement.io.save_poses.to_lp_file", "info": ""}
{"filename": "api_index.rst", "lineno": 1, "status": "unchecked", "code": 0, "uri": "#movement.io.save_poses.to_sleap_analysis_file", "info": ""}
{"filename": "api_index.rst", "lineno": 1, "status": "unchecked", "code": 0, "uri": "#movement.io.validators.ValidFile", "info": ""}
{"filename": "api_index.rst", "lineno": 1, "status": "unchecked", "code": 0, "uri": "#movement.io.validators.ValidHDF5", "info": ""}
{"filename": "api_index.rst", "lineno": 1, "status": "unchecked", "code": 0, "uri": "#movement.io.validators.ValidPosesCSV", "info": ""}
{"filename": "api_index.rst", "lineno": 1, "status": "unchecked", "code": 0, "uri": "#movement.io.validators.ValidPosesDataset", "info": ""}
{"filename": "api_index.rst", "lineno": 1, "status": "unchecked", "code": 0, "uri": "#movement.logging.configure_logging", "info": ""}
{"filename": "api_index.rst", "lineno": 1, "status": "unchecked", "code": 0, "uri": "#movement.logging.log_error", "info": ""}
{"filename": "api_index.rst", "lineno": 1, "status": "unchecked", "code": 0, "uri": "#movement.logging.log_warning", "info": ""}
{"filename": "api_index.rst", "lineno": 1, "status": "unchecked", "code": 0, "uri": "#movement.move_accessor.MovementDataset", "info": ""}
{"filename": "api/movement.sample_data.fetch_dataset_paths.rst", "lineno": 24, "status": "unchecked", "code": 0, "uri": "#movement.sample_data.fetch_dataset", "info": ""}
{"filename": "api/movement.sample_data.fetch_dataset.rst", "lineno": 23, "status": "unchecked", "code": 0, "uri": "#movement.sample_data.fetch_dataset_paths", "info": ""}
{"filename": "api_index.rst", "lineno": 1, "status": "unchecked", "code": 0, "uri": "#movement.sample_data.list_datasets", "info": ""}
{"filename": "api_index.rst", "lineno": 1, "status": "unchecked", "code": 0, "uri": "#movement.utils.vector.cart2pol", "info": ""}
{"filename": "api_index.rst", "lineno": 1, "status": "unchecked", "code": 0, "uri": "#movement.utils.vector.pol2cart", "info": ""}
{"filename": "examples/sg_execution_times.rst", "lineno": 41, "status": "unchecked", "code": 0, "uri": "#sphx-glr-examples-compute-kinematics-py", "info": ""}
{"filename": "examples/sg_execution_times.rst", "lineno": 38, "status": "unchecked", "code": 0, "uri": "#sphx-glr-examples-filter-and-interpolate-py", "info": ""}
{"filename": "examples/sg_execution_times.rst", "lineno": 35, "status": "unchecked", "code": 0, "uri": "#sphx-glr-examples-load-and-explore-poses-py", "info": ""}
{"filename": "community/contributing.rst", "lineno": 212, "status": "unchecked", "code": 0, "uri": "#target-api", "info": ""}
{"filename": "community/index.md", "lineno": 3, "status": "unchecked", "code": 0, "uri": "#target-contributing", "info": ""}
{"filename": "getting_started/input_output.md", "lineno": 87, "status": "unchecked", "code": 0, "uri": "#target-dataset", "info": ""}
{"filename": "community/contributing.rst", "lineno": 232, "status": "unchecked", "code": 0, "uri": "#target-examples", "info": ""}
{"filename": "getting_started/index.md", "lineno": 5, "status": "unchecked", "code": 0, "uri": "#target-formats", "info": ""}
{"filename": "getting_started/index.md", "lineno": 5, "status": "unchecked", "code": 0, "uri": "#target-loading", "info": ""}
{"filename": "community/index.md", "lineno": 3, "status": "unchecked", "code": 0, "uri": "#target-mission", "info": ""}
{"filename": "community/contributing.rst", "lineno": 162, "status": "unchecked", "code": 0, "uri": "#target-movement", "info": ""}
{"filename": "community/index.md", "lineno": 3, "status": "unchecked", "code": 0, "uri": "#target-roadmaps", "info": ""}
{"filename": "getting_started/index.md", "lineno": 5, "status": "unchecked", "code": 0, "uri": "#target-sample-data", "info": ""}
{"filename": "getting_started/sample_data.md", "lineno": 4, "status": "unchecked", "code": 0, "uri": "#target-supported-formats", "info": ""}
{"filename": "community/contributing.rst", "lineno": 128, "status": "working", "code": 0, "uri": "https://docs.github.com/en/actions#", "info": ""}
{"filename": "community/contributing.rst", "lineno": 50, "status": "working", "code": 0, "uri": "https://docs.github.com/en/pull-requests/collaborating-with-pull-requests/incorporating-changes-from-a-pull-request/about-pull-request-merges#squash-and-merge-your-commits", "info": ""}
{"filename": "community/contributing.rst", "lineno": 7, "status": "working", "code": 0, "uri": "https://docs.conda.io/en/latest/", "info": ""}
{"filename": "api/movement.move_accessor.MovementDataset.rst", "lineno": 15, "status": "working", "code": 0, "uri": "https://docs.xarray.dev/en/stable/internals/extending-xarray.html", "info": ""}
{"filename": "getting_started/movement_dataset.md", "lineno": 81, "status": "working", "code": 0, "uri": "https://docs.xarray.dev/en/stable/user-guide/computation.html#", "info": ""}
{"filename": "community/roadmaps.md", "lineno": 12, "status": "working", "code": 0, "uri": "https://docs.xarray.dev/en/stable/user-guide/data-structures.html#", "info": ""}
{"filename": "getting_started/movement_dataset.md", "lineno": 81, "status": "working", "code": 0, "uri": "https://docs.xarray.dev/en/stable/user-guide/indexing.html#", "info": ""}
{"filename": "getting_started/movement_dataset.md", "lineno": 81, "status": "working", "code": 0, "uri": "https://docs.xarray.dev/en/stable/user-guide/plotting.html#", "info": ""}
{"filename": "getting_started/movement_dataset.md", "lineno": 35, "status": "working", "code": 0, "uri": "https://docs.xarray.dev/en/stable/user-guide/terminology.html#", "info": ""}
{"filename": "community/roadmaps.md", "lineno": 27, "status": "working", "code": 0, "uri": "https://conda-forge.org/", "info": ""}
{"filename": "community/contributing.rst", "lineno": 116, "status": "working", "code": 0, "uri": "https://docs.pytest.org/en/latest/", "info": ""}
{"filename": "community/contributing.rst", "lineno": 107, "status": "working", "code": 0, "uri": "https://docs.astral.sh/ruff/rules/", "info": ""}
{"filename": "community/contributing.rst", "lineno": 162, "status": "working", "code": 0, "uri": "https://docutils.sourceforge.io/rst.html", "info": ""}
{"filename": "community/contributing.rst", "lineno": 62, "status": "working", "code": 0, "uri": "https://github.blog/changelog/2023-02-08-pull-request-merge-queue-public-beta/", "info": ""}
{"filename": "community/contributing.rst", "lineno": 284, "status": "working", "code": 0, "uri": "https://gin.g-node.org/#", "info": ""}
{"filename": "community/related-projects.md", "lineno": 4, "status": "working", "code": 0, "uri": "https://github.com/AdaptiveMotorControlLab/DLC2Kinematics", "info": ""}
{"filename": "community/related-projects.md", "lineno": 6, "status": "working", "code": 0, "uri": "https://github.com/BrancoLab/Kino", "info": ""}
{"filename": "community/contributing.rst", "lineno": 284, "status": "working", "code": 0, "uri": "https://gin.g-node.org/G-Node/Info/wiki/GIN+CLI+Setup#quickstart", "info": ""}
{"filename": "community/contributing.rst", "lineno": 70, "status": "working", "code": 0, "uri": "https://github.com/astral-sh/ruff", "info": ""}
{"filename": "community/related-projects.md", "lineno": 7, "status": "working", "code": 0, "uri": "https://github.com/SainsburyWellcomeCentre/WAZP", "info": ""}
{"filename": "community/contributing.rst", "lineno": 73, "status": "working", "code": 0, "uri": "https://github.com/codespell-project/codespell", "info": ""}
{"filename": "community/contributing.rst", "lineno": 72, "status": "working", "code": 0, "uri": "https://github.com/mgedmin/check-manifest", "info": ""}
{"filename": "community/contributing.rst", "lineno": 284, "status": "working", "code": 0, "uri": "https://gin.g-node.org/neuroinformatics/movement-test-data#", "info": ""}
{"filename": "community/index.md", "lineno": 3, "status": "working", "code": 0, "uri": "https://github.com/neuroinformatics-unit/movement/issues", "info": ""}
{"filename": "community/roadmaps.md", "lineno": 22, "status": "working", "code": 0, "uri": "https://lightning-pose.readthedocs.io/en/stable/#", "info": ""}
{"filename": "getting_started/installation.md", "lineno": 44, "status": "working", "code": 0, "uri": "https://github.com/neuroinformatics-unit/movement/", "info": ""}
{"filename": "community/contributing.rst", "lineno": 7, "status": "working", "code": 0, "uri": "https://mamba.readthedocs.io/en/latest/", "info": ""}
{"filename": "community/contributing.rst", "lineno": 203, "status": "working", "code": 0, "uri": "https://github.com/neuroinformatics-unit/movement/issues/1", "info": ""}
{"filename": "community/contributing.rst", "lineno": 71, "status": "working", "code": 0, "uri": "https://mypy.readthedocs.io/en/stable/index.html", "info": ""}
{"filename": "community/contributing.rst", "lineno": 208, "status": "working", "code": 0, "uri": "https://myst-parser.readthedocs.io/en/latest/syntax/cross-referencing.html#customising-external-url-resolution", "info": ""}
{"filename": "community/contributing.rst", "lineno": 162, "status": "working", "code": 0, "uri": "https://myst-parser.readthedocs.io/en/latest/syntax/typography.html#", "info": ""}
{"filename": "community/contributing.rst", "lineno": 238, "status": "working", "code": 0, "uri": "https://mybinder.readthedocs.io/en/latest/using/config_files.html", "info": ""}
{"filename": "api/movement.io.load_poses.from_sleap_file.rst", "lineno": 42, "status": "working", "code": 0, "uri": "https://github.com/talmolab/sleap/blob/v1.3.3/sleap/info/write_tracking_h5.py#L59", "info": ""}
{"filename": "community/related-projects.md", "lineno": 5, "status": "working", "code": 0, "uri": "https://github.com/pyratlib/pyrat", "info": ""}
{"filename": "community/roadmaps.md", "lineno": 13, "status": "working", "code": 0, "uri": "https://napari.org/dev/", "info": ""}
{"filename": "community/mission-scope.md", "lineno": 27, "status": "working", "code": 0, "uri": "https://napari.org/dev/community/mission_and_values", "info": ""}
{"filename": "community/roadmaps.md", "lineno": 28, "status": "working", "code": 0, "uri": "https://napari.org/dev/howtos/layers/tracks", "info": ""}
{"filename": "community/contributing.rst", "lineno": 110, "status": "working", "code": 0, "uri": "https://numpydoc.readthedocs.io/en/latest/format.html", "info": ""}
{"filename": "community/index.md", "lineno": 3, "status": "working", "code": 0, "uri": "https://neuroinformatics.zulipchat.com/#narrow/stream/406001-Movement", "info": ""}
{"filename": "community/contributing.rst", "lineno": 162, "status": "working", "code": 0, "uri": "https://pages.github.com/", "info": ""}
{"filename": "community/roadmaps.md", "lineno": 26, "status": "working", "code": 0, "uri": "https://pypi.org/project/movement/", "info": ""}
{"filename": "community/contributing.rst", "lineno": 170, "status": "working", "code": 0, "uri": "https://pydata-sphinx-theme.readthedocs.io/en/stable/index.html", "info": ""}
{"filename": "community/roadmaps.md", "lineno": 28, "status": "working", "code": 0, "uri": "https://napari.org/dev/howtos/layers/points", "info": ""}
{"filename": "community/contributing.rst", "lineno": 143, "status": "working", "code": 0, "uri": "https://setuptools-scm.readthedocs.io/en/latest/#", "info": ""}
{"filename": "community/contributing.rst", "lineno": 69, "status": "working", "code": 0, "uri": "https://pre-commit.com/", "info": ""}
{"filename": "community/license.md", "lineno": 3, "status": "working", "code": 0, "uri": "https://opensource.org/license/bsd-3-clause/", "info": ""}
{"filename": "community/contributing.rst", "lineno": 137, "status": "working", "code": 0, "uri": "https://semver.org/", "info": ""}
{"filename": "community/contributing.rst", "lineno": 143, "status": "working", "code": 0, "uri": "https://setuptools-scm.readthedocs.io/en/latest/usage#default-versioning-scheme", "info": ""}
{"filename": "api/movement.io.save_poses.to_sleap_analysis_file.rst", "lineno": 28, "status": "working", "code": 0, "uri": "https://sleap.ai/api/sleap.info.write_tracking_h5.html", "info": ""}
{"filename": "getting_started/input_output.md", "lineno": 119, "status": "working", "code": 0, "uri": "https://sleap.ai/api/sleap.info.write_tracking_h5.html#module-sleap.info.write_tracking_h5", "info": ""}
{"filename": "community/mission-scope.md", "lineno": 10, "status": "working", "code": 0, "uri": "https://sleap.ai/#", "info": ""}
{"filename": "getting_started/input_output.md", "lineno": 35, "status": "working", "code": 0, "uri": "https://sleap.ai/tutorials/analysis#", "info": ""}
{"filename": "api/movement.io.load_poses.from_sleap_file.rst", "lineno": 43, "status": "working", "code": 0, "uri": "https://sleap.ai/guides/proofreading.html", "info": ""}
{"filename": "api/movement.io.load_poses.from_sleap_file.rst", "lineno": 41, "status": "working", "code": 0, "uri": "https://sleap.ai/tutorials/analysis.html", "info": ""}
{"filename": "community/contributing.rst", "lineno": 232, "status": "working", "code": 0, "uri": "https://sphinx-gallery.github.io/stable/syntax", "info": ""}
{"filename": "community/contributing.rst", "lineno": 232, "status": "working", "code": 0, "uri": "https://sphinx-gallery.github.io/stable/", "info": ""}
{"filename": "community/contributing.rst", "lineno": 238, "status": "working", "code": 0, "uri": "https://sphinx-gallery.github.io/stable/configuration.html#binder-links", "info": ""}
{"filename": "community/contributing.rst", "lineno": 301, "status": "working", "code": 0, "uri": "https://www.fatiando.org/pooch/latest/index.html", "info": ""}
{"filename": "community/contributing.rst", "lineno": 170, "status": "working", "code": 0, "uri": "https://www.sphinx-doc.org/en/master/", "info": ""}
{"filename": "community/mission-scope.md", "lineno": 10, "status": "working", "code": 0, "uri": "https://www.mackenziemathislab.org/deeplabcut/", "info": ""}
{"filename": "community/contributing.rst", "lineno": 284, "status": "working", "code": 0, "uri": "https://www.g-node.org/", "info": ""}
{"filename": "community/contributing.rst", "lineno": 19, "status": "working", "code": 0, "uri": "https://www.hdfgroup.org/solutions/hdf5/", "info": ""}
